transforms_fake/__init__.py
transforms_fake/main.py
transforms_fake/process_images.py
transforms_fake/rotate_image_and_mask.py
transforms_fake-0.1.4.dist-info/licenses/LICENSE
transforms_fake-0.1.4.dist-info/METADATA
transforms_fake-0.1.4.dist-info/WHEEL
transforms_fake-0.1.4.dist-info/top_level.txt
transforms_fake-0.1.4.dist-info/RECORD
