Metadata-Version: 2.4
Name: transforms_fake
Version: 0.1.4
Summary: A Python library for generating realistic synthetic images to train segmentation models in a smart, simple way.
Author-email: "Peres; RB, Borges; CA" <founder@thotiacorp.com.br>
License:                     GNU GENERAL PUBLIC LICENSE
Project-URL: Homepage, https://github.com/THOTIACORP/transforms_fake.git
Requires-Python: >=3.9.13
License-File: LICENSE
Requires-Dist: opencv-python>=4.5.0
Requires-Dist: numpy>=1.19.0
Requires-Dist: PyQt5>=5.15.0
Dynamic: license-file
